Metadata-Version: 2.4
Name: skill-mcp-fastmcp
Version: 0.1.2
Summary: A Model Context Protocol (MCP) server for managing Claude skills
Project-URL: Homepage, https://github.com/fastmcp-me/skill-mcp#readme
Project-URL: Repository, https://github.com/fastmcp-me/skill-mcp.git
Project-URL: Issues, https://github.com/fastmcp-me/skill-mcp/issues
Author: fkesheh
License: MIT
License-File: LICENSE
Keywords: ai,claude,llm,mcp,model-context-protocol,skills
Classifier: Development Status :: 4 - Beta
Classifier: Environment :: Console
Classifier: Intended Audience :: Developers
Classifier: License :: OSI Approved :: MIT License
Classifier: Natural Language :: English
Classifier: Operating System :: OS Independent
Classifier: Programming Language :: Python :: 3
Classifier: Programming Language :: Python :: 3.10
Classifier: Programming Language :: Python :: 3.11
Classifier: Programming Language :: Python :: 3.12
Classifier: Topic :: Software Development :: Libraries :: Python Modules
Classifier: Topic :: System :: Systems Administration
Requires-Python: >=3.10
Requires-Dist: mcp>=1.0.0
Requires-Dist: pydantic>=2.0.0
Requires-Dist: python-dotenv>=1.0.0
Requires-Dist: pyyaml>=6.0.0
